ghettorecorder/__init__.py
ghettorecorder/__main__.py
ghettorecorder/audio_conf.py
ghettorecorder/blacklist.json
ghettorecorder/cmd.py
ghettorecorder/ghetto_agents.py
ghettorecorder/ghetto_api.py
ghettorecorder/ghetto_api_feeder.py
ghettorecorder/ghetto_blacklist.py
ghettorecorder/ghetto_container.py
ghettorecorder/ghetto_db_worker.py
ghettorecorder/ghetto_header_aac.py
ghettorecorder/ghetto_header_mp3.py
ghettorecorder/ghetto_http_simple.py
ghettorecorder/ghetto_ini.py
ghettorecorder/ghetto_menu.py
ghettorecorder/ghetto_meta.py
ghettorecorder/ghetto_net.py
ghettorecorder/ghetto_procenv.py
ghettorecorder/ghetto_recorder.ascii
ghettorecorder/ghetto_recorder.menu_info
ghettorecorder/ghetto_recorder.py
ghettorecorder/ghetto_utils.py
ghettorecorder/index.html
ghettorecorder/schema.sql
ghettorecorder/settings.ini
ghettorecorder/static/css/style.css
ghettorecorder/static/images/airplane_forbidden_opti.svg
ghettorecorder/static/images/ghetto_url.svg
ghettorecorder/static/images/gr_sky.svg
ghettorecorder/static/images/gr_sky_basket.svg
ghettorecorder/static/js/animate.js
ghettorecorder/static/js/index.js
ghettorecorder-3.1.dist-info/LICENSE.rst
ghettorecorder-3.1.dist-info/METADATA
ghettorecorder-3.1.dist-info/WHEEL
ghettorecorder-3.1.dist-info/top_level.txt
ghettorecorder-3.1.dist-info/zip-safe
ghettorecorder-3.1.dist-info/RECORD
